{
  "slug": "silverado-1985",
  "title": "Silverado",
  "imdb_id": "tt0090022",
  "year": 1985,
  "token_count": 40260,
  "main_arc": [
    {
      "position": 0.05,
      "z_score": 0.4628967139158945
    },
    {
      "position": 0.1,
      "z_score": -0.24766715109434967
    },
    {
      "position": 0.15,
      "z_score": -1.2241380210730712
    },
    {
      "position": 0.2,
      "z_score": -2.2167121056966526
    },
    {
      "position": 0.25,
      "z_score": -0.7433397149919972
    },
    {
      "position": 0.3,
      "z_score": -0.5923190740952198
    },
    {
      "position": 0.35,
      "z_score": 1.4808968822313198
    },
    {
      "position": 0.4,
      "z_score": 0.9589816627741804
    },
    {
      "position": 0.45,
      "z_score": -0.6250377510904819
    },
    {
      "position": 0.5,
      "z_score": -1.2305669935197876
    },
    {
      "position": 0.55,
      "z_score": 0.35726464592865165
    },
    {
      "position": 0.6,
      "z_score": 1.5206115528287838
    },
    {
      "position": 0.65,
      "z_score": 0.43052473946753383
    },
    {
      "position": 0.7,
      "z_score": -0.6923707825018408
    },
    {
      "position": 0.75,
      "z_score": -0.9230548337223619
    },
    {
      "position": 0.8,
      "z_score": 0.41259882967607847
    },
    {
      "position": 0.85,
      "z_score": 1.4882003518369633
    },
    {
      "position": 0.9,
      "z_score": 0.9403937356560039
    },
    {
      "position": 0.95,
      "z_score": 0.4044065244830489
    },
    {
      "position": 0.975,
      "z_score": 0.03843078898730101
    }
  ],
  "secondary_arc": [
    {
      "position": 0.018628912071535022,
      "smoothed_score": 0.10132732093334233
    },
    {
      "position": 0.031048186785891704,
      "smoothed_score": -0.08456868529319746
    },
    {
      "position": 0.04346746150024838,
      "smoothed_score": -0.08833426535129553
    },
    {
      "position": 0.05588673621460507,
      "smoothed_score": 0.09696995999131872
    },
    {
      "position": 0.06830601092896176,
      "smoothed_score": 0.37673872666699526
    },
    {
      "position": 0.08072528564331843,
      "smoothed_score": 0.5400139540433881
    },
    {
      "position": 0.09314456035767511,
      "smoothed_score": 0.5399155114378245
    },
    {
      "position": 0.10556383507203179,
      "smoothed_score": 0.32758563331195256
    },
    {
      "position": 0.11798310978638847,
      "smoothed_score": 0.29333676610674153
    },
    {
      "position": 0.13040238450074515,
      "smoothed_score": 0.19199323185852582
    },
    {
      "position": 0.14282165921510184,
      "smoothed_score": 0.08245360127517135
    },
    {
      "position": 0.1552409339294585,
      "smoothed_score": 0.24557540161269023
    },
    {
      "position": 0.1676602086438152,
      "smoothed_score": 0.6367899579661231
    },
    {
      "position": 0.1800794833581719,
      "smoothed_score": 0.6202643181596483
    },
    {
      "position": 0.19249875807252856,
      "smoothed_score": -0.20953445179121824
    },
    {
      "position": 0.20491803278688525,
      "smoothed_score": -0.8442404036011012
    },
    {
      "position": 0.21733730750124192,
      "smoothed_score": -1.0199360059840337
    },
    {
      "position": 0.2297565822155986,
      "smoothed_score": -0.3599215226513997
    },
    {
      "position": 0.2421758569299553,
      "smoothed_score": 0.33014135318143034
    },
    {
      "position": 0.25459513164431197,
      "smoothed_score": 0.41265737925256984
    },
    {
      "position": 0.26701440635866863,
      "smoothed_score": 0.25600028719220813
    },
    {
      "position": 0.27943368107302535,
      "smoothed_score": 0.3256751899208339
    },
    {
      "position": 0.291852955787382,
      "smoothed_score": 0.5356891572475431
    },
    {
      "position": 0.3042722305017387,
      "smoothed_score": 0.491490446243967
    },
    {
      "position": 0.3166915052160954,
      "smoothed_score": 0.4907012202910011
    },
    {
      "position": 0.32911077993045207,
      "smoothed_score": 0.4521022490092682
    },
    {
      "position": 0.34153005464480873,
      "smoothed_score": 0.618243082932063
    },
    {
      "position": 0.3539493293591654,
      "smoothed_score": 0.8573022412402285
    },
    {
      "position": 0.3663686040735221,
      "smoothed_score": 1.0309388237340102
    },
    {
      "position": 0.3787878787878788,
      "smoothed_score": 1.0716794908046716
    },
    {
      "position": 0.39120715350223545,
      "smoothed_score": 0.7260068723133628
    },
    {
      "position": 0.40362642821659217,
      "smoothed_score": 0.24598966709205053
    },
    {
      "position": 0.41604570293094884,
      "smoothed_score": -0.11956606635025588
    },
    {
      "position": 0.4284649776453055,
      "smoothed_score": 0.0957647349153244
    },
    {
      "position": 0.4408842523596622,
      "smoothed_score": 0.544072706358773
    },
    {
      "position": 0.4533035270740189,
      "smoothed_score": 0.8138355037995744
    },
    {
      "position": 0.46572280178837555,
      "smoothed_score": 0.5337389856576917
    },
    {
      "position": 0.4781420765027322,
      "smoothed_score": 0.07451345622539501
    },
    {
      "position": 0.49056135121708894,
      "smoothed_score": -0.053574918423380226
    },
    {
      "position": 0.5029806259314457,
      "smoothed_score": -0.02060935710157667
    },
    {
      "position": 0.5153999006458023,
      "smoothed_score": 0.016144905771527968
    },
    {
      "position": 0.527819175360159,
      "smoothed_score": -0.015203911491802821
    },
    {
      "position": 0.5402384500745157,
      "smoothed_score": 0.13308724931308186
    },
    {
      "position": 0.5526577247888723,
      "smoothed_score": 0.37988840980189165
    },
    {
      "position": 0.565076999503229,
      "smoothed_score": 0.48800199755600493
    },
    {
      "position": 0.5774962742175856,
      "smoothed_score": 0.636541652679443
    },
    {
      "position": 0.5899155489319424,
      "smoothed_score": 0.717984112671443
    },
    {
      "position": 0.6023348236462991,
      "smoothed_score": 0.7050740092992778
    },
    {
      "position": 0.6147540983606558,
      "smoothed_score": 0.4801387544189176
    },
    {
      "position": 0.6271733730750124,
      "smoothed_score": 0.5317663959094453
    },
    {
      "position": 0.6395926477893691,
      "smoothed_score": 0.36684767646448935
    },
    {
      "position": 0.6520119225037257,
      "smoothed_score": 0.11873409237180421
    },
    {
      "position": 0.6644311972180824,
      "smoothed_score": -0.048628618461745265
    },
    {
      "position": 0.6768504719324392,
      "smoothed_score": 0.2539235685552869
    },
    {
      "position": 0.6892697466467959,
      "smoothed_score": 0.16615057885646828
    },
    {
      "position": 0.7016890213611525,
      "smoothed_score": -0.2220857215779168
    },
    {
      "position": 0.7141082960755092,
      "smoothed_score": -0.4761513356651578
    },
    {
      "position": 0.7265275707898659,
      "smoothed_score": -0.007103843348366879
    },
    {
      "position": 0.7389468455042225,
      "smoothed_score": 0.4510197107281003
    },
    {
      "position": 0.7513661202185792,
      "smoothed_score": 0.4081653228827884
    },
    {
      "position": 0.763785394932936,
      "smoothed_score": 0.12383590596062781
    },
    {
      "position": 0.7762046696472926,
      "smoothed_score": -0.12686992245061074
    },
    {
      "position": 0.7886239443616493,
      "smoothed_score": 0.30090831560747944
    },
    {
      "position": 0.801043219076006,
      "smoothed_score": 0.5752414252076827
    },
    {
      "position": 0.8134624937903626,
      "smoothed_score": 0.8405489832162851
    },
    {
      "position": 0.8258817685047193,
      "smoothed_score": 0.8253438268389015
    },
    {
      "position": 0.8383010432190761,
      "smoothed_score": 1.025965080090931
    },
    {
      "position": 0.8507203179334327,
      "smoothed_score": 0.9812551200389856
    },
    {
      "position": 0.8631395926477894,
      "smoothed_score": 0.9841228263718734
    },
    {
      "position": 0.875558867362146,
      "smoothed_score": 1.0780565440654748
    },
    {
      "position": 0.8879781420765027,
      "smoothed_score": 0.6541076166289188
    },
    {
      "position": 0.9003974167908594,
      "smoothed_score": 0.5521245287997376
    },
    {
      "position": 0.912816691505216,
      "smoothed_score": 0.4819383987358633
    },
    {
      "position": 0.9252359662195728,
      "smoothed_score": 0.878454922352518
    },
    {
      "position": 0.9376552409339295,
      "smoothed_score": 0.7762032559939789
    },
    {
      "position": 0.9500745156482862,
      "smoothed_score": 0.427329412954194
    },
    {
      "position": 0.9624937903626428,
      "smoothed_score": -0.3260682553052903
    },
    {
      "position": 0.9749130650769995,
      "smoothed_score": -0.24373002222606113
    },
    {
      "position": 0.9843517138599106,
      "smoothed_score": 0.036152283634458215
    },
    {
      "position": 0.9905613512170889,
      "smoothed_score": 0.40987228368009837
    },
    {
      "position": 0.9967709885742673,
      "smoothed_score": 0.8672070013625282
    }
  ]
}