{
  "window": 3000,
  "step": 500,
  "windows": [
    {
      "start": 0,
      "end": 3000,
      "tokens": 3000,
      "coverage": 0.829,
      "happiness": 5.413952553277003
    },
    {
      "start": 500,
      "end": 3500,
      "tokens": 3000,
      "coverage": 0.834,
      "happiness": 5.444768185451603
    },
    {
      "start": 1000,
      "end": 4000,
      "tokens": 3000,
      "coverage": 0.8413333333333334,
      "happiness": 5.48301109350235
    },
    {
      "start": 1500,
      "end": 4500,
      "tokens": 3000,
      "coverage": 0.848,
      "happiness": 5.468427672955943
    },
    {
      "start": 2000,
      "end": 5000,
      "tokens": 3000,
      "coverage": 0.8483333333333334,
      "happiness": 5.472361493123731
    },
    {
      "start": 2500,
      "end": 5500,
      "tokens": 3000,
      "coverage": 0.8293333333333334,
      "happiness": 5.464288585208958
    },
    {
      "start": 3000,
      "end": 6000,
      "tokens": 3000,
      "coverage": 0.83,
      "happiness": 5.46190361445777
    },
    {
      "start": 3500,
      "end": 6500,
      "tokens": 3000,
      "coverage": 0.8303333333333334,
      "happiness": 5.443512645523825
    },
    {
      "start": 4000,
      "end": 7000,
      "tokens": 3000,
      "coverage": 0.8183333333333334,
      "happiness": 5.394407331975523
    },
    {
      "start": 4500,
      "end": 7500,
      "tokens": 3000,
      "coverage": 0.8166666666666667,
      "happiness": 5.428204081632626
    },
    {
      "start": 5000,
      "end": 8000,
      "tokens": 3000,
      "coverage": 0.8133333333333334,
      "happiness": 5.426512295081927
    },
    {
      "start": 5500,
      "end": 8500,
      "tokens": 3000,
      "coverage": 0.8276666666666667,
      "happiness": 5.433616592831189
    },
    {
      "start": 6000,
      "end": 9000,
      "tokens": 3000,
      "coverage": 0.8293333333333334,
      "happiness": 5.440430064308635
    },
    {
      "start": 6500,
      "end": 9500,
      "tokens": 3000,
      "coverage": 0.8366666666666667,
      "happiness": 5.426569721115494
    },
    {
      "start": 7000,
      "end": 10000,
      "tokens": 3000,
      "coverage": 0.8563333333333333,
      "happiness": 5.444149474503669
    },
    {
      "start": 7500,
      "end": 10500,
      "tokens": 3000,
      "coverage": 0.8663333333333333,
      "happiness": 5.443551365909935
    },
    {
      "start": 8000,
      "end": 11000,
      "tokens": 3000,
      "coverage": 0.872,
      "happiness": 5.432572629969376
    },
    {
      "start": 8500,
      "end": 11500,
      "tokens": 3000,
      "coverage": 0.8753333333333333,
      "happiness": 5.4229093678598215
    },
    {
      "start": 9000,
      "end": 12000,
      "tokens": 3000,
      "coverage": 0.878,
      "happiness": 5.415675778283946
    },
    {
      "start": 9500,
      "end": 12500,
      "tokens": 3000,
      "coverage": 0.8786666666666667,
      "happiness": 5.439738239757177
    },
    {
      "start": 10000,
      "end": 13000,
      "tokens": 3000,
      "coverage": 0.8833333333333333,
      "happiness": 5.449709433962234
    },
    {
      "start": 10500,
      "end": 13500,
      "tokens": 3000,
      "coverage": 0.8823333333333333,
      "happiness": 5.457548167737025
    },
    {
      "start": 11000,
      "end": 14000,
      "tokens": 3000,
      "coverage": 0.886,
      "happiness": 5.470289691497331
    },
    {
      "start": 11500,
      "end": 14500,
      "tokens": 3000,
      "coverage": 0.892,
      "happiness": 5.483688340807139
    },
    {
      "start": 12000,
      "end": 15000,
      "tokens": 3000,
      "coverage": 0.894,
      "happiness": 5.4931319910514125
    },
    {
      "start": 12500,
      "end": 15500,
      "tokens": 3000,
      "coverage": 0.8863333333333333,
      "happiness": 5.500541556976276
    },
    {
      "start": 13000,
      "end": 16000,
      "tokens": 3000,
      "coverage": 0.8733333333333333,
      "happiness": 5.511576335877821
    },
    {
      "start": 13500,
      "end": 16500,
      "tokens": 3000,
      "coverage": 0.8663333333333333,
      "happiness": 5.525502116198497
    },
    {
      "start": 14000,
      "end": 17000,
      "tokens": 3000,
      "coverage": 0.8626666666666667,
      "happiness": 5.522187017001511
    },
    {
      "start": 14500,
      "end": 17500,
      "tokens": 3000,
      "coverage": 0.8623333333333333,
      "happiness": 5.518581368380343
    },
    {
      "start": 15000,
      "end": 18000,
      "tokens": 3000,
      "coverage": 0.8643333333333333,
      "happiness": 5.516432703432294
    },
    {
      "start": 15500,
      "end": 18500,
      "tokens": 3000,
      "coverage": 0.8716666666666667,
      "happiness": 5.500252390057341
    },
    {
      "start": 16000,
      "end": 19000,
      "tokens": 3000,
      "coverage": 0.873,
      "happiness": 5.48516991218018
    },
    {
      "start": 16500,
      "end": 19500,
      "tokens": 3000,
      "coverage": 0.88,
      "happiness": 5.468200757575718
    },
    {
      "start": 17000,
      "end": 20000,
      "tokens": 3000,
      "coverage": 0.8856666666666667,
      "happiness": 5.474113662024798
    },
    {
      "start": 17500,
      "end": 20500,
      "tokens": 3000,
      "coverage": 0.8816666666666667,
      "happiness": 5.479406427221131
    },
    {
      "start": 18000,
      "end": 21000,
      "tokens": 3000,
      "coverage": 0.8753333333333333,
      "happiness": 5.482361005331268
    },
    {
      "start": 18500,
      "end": 21500,
      "tokens": 3000,
      "coverage": 0.8756666666666667,
      "happiness": 5.471301865245494
    },
    {
      "start": 19000,
      "end": 22000,
      "tokens": 3000,
      "coverage": 0.8726666666666667,
      "happiness": 5.478250572956426
    },
    {
      "start": 19500,
      "end": 22500,
      "tokens": 3000,
      "coverage": 0.8623333333333333,
      "happiness": 5.455144955546928
    },
    {
      "start": 20000,
      "end": 23000,
      "tokens": 3000,
      "coverage": 0.8573333333333333,
      "happiness": 5.440707620528725
    },
    {
      "start": 20500,
      "end": 23500,
      "tokens": 3000,
      "coverage": 0.843,
      "happiness": 5.405203637801456
    },
    {
      "start": 21000,
      "end": 24000,
      "tokens": 3000,
      "coverage": 0.8396666666666667,
      "happiness": 5.374954346963047
    },
    {
      "start": 21500,
      "end": 24500,
      "tokens": 3000,
      "coverage": 0.8346666666666667,
      "happiness": 5.362539936102208
    },
    {
      "start": 22000,
      "end": 25000,
      "tokens": 3000,
      "coverage": 0.8416666666666667,
      "happiness": 5.35813861386136
    },
    {
      "start": 22500,
      "end": 25500,
      "tokens": 3000,
      "coverage": 0.842,
      "happiness": 5.350546318289752
    },
    {
      "start": 23000,
      "end": 26000,
      "tokens": 3000,
      "coverage": 0.8376666666666667,
      "happiness": 5.325320334261807
    },
    {
      "start": 23500,
      "end": 26500,
      "tokens": 3000,
      "coverage": 0.842,
      "happiness": 5.338079968329324
    },
    {
      "start": 24000,
      "end": 27000,
      "tokens": 3000,
      "coverage": 0.8416666666666667,
      "happiness": 5.353596039603924
    },
    {
      "start": 24500,
      "end": 27500,
      "tokens": 3000,
      "coverage": 0.8423333333333334,
      "happiness": 5.350451127819515
    },
    {
      "start": 25000,
      "end": 28000,
      "tokens": 3000,
      "coverage": 0.8393333333333334,
      "happiness": 5.3511715647338844
    },
    {
      "start": 25500,
      "end": 28500,
      "tokens": 3000,
      "coverage": 0.8426666666666667,
      "happiness": 5.348568037974642
    },
    {
      "start": 26000,
      "end": 29000,
      "tokens": 3000,
      "coverage": 0.8526666666666667,
      "happiness": 5.38081704456604
    },
    {
      "start": 26500,
      "end": 29500,
      "tokens": 3000,
      "coverage": 0.8603333333333333,
      "happiness": 5.3694033320418235
    },
    {
      "start": 27000,
      "end": 30000,
      "tokens": 3000,
      "coverage": 0.8666666666666667,
      "happiness": 5.361246153846129
    },
    {
      "start": 27500,
      "end": 30500,
      "tokens": 3000,
      "coverage": 0.8683333333333333,
      "happiness": 5.378234165067138
    },
    {
      "start": 28000,
      "end": 31000,
      "tokens": 3000,
      "coverage": 0.8686666666666667,
      "happiness": 5.373603223330736
    },
    {
      "start": 28500,
      "end": 31500,
      "tokens": 3000,
      "coverage": 0.8693333333333333,
      "happiness": 5.377722392638009
    },
    {
      "start": 29000,
      "end": 32000,
      "tokens": 3000,
      "coverage": 0.8613333333333333,
      "happiness": 5.354667182662502
    },
    {
      "start": 29500,
      "end": 32500,
      "tokens": 3000,
      "coverage": 0.8563333333333333,
      "happiness": 5.355889451148268
    },
    {
      "start": 30000,
      "end": 33000,
      "tokens": 3000,
      "coverage": 0.8616666666666667,
      "happiness": 5.375029013539632
    },
    {
      "start": 30500,
      "end": 33500,
      "tokens": 3000,
      "coverage": 0.8696666666666667,
      "happiness": 5.35722499041776
    },
    {
      "start": 31000,
      "end": 34000,
      "tokens": 3000,
      "coverage": 0.8643333333333333,
      "happiness": 5.359591207095994
    },
    {
      "start": 31500,
      "end": 34500,
      "tokens": 3000,
      "coverage": 0.8643333333333333,
      "happiness": 5.351079830312338
    },
    {
      "start": 32000,
      "end": 35000,
      "tokens": 3000,
      "coverage": 0.8666666666666667,
      "happiness": 5.3500192307691945
    },
    {
      "start": 32500,
      "end": 35500,
      "tokens": 3000,
      "coverage": 0.87,
      "happiness": 5.344164750957814
    },
    {
      "start": 33000,
      "end": 36000,
      "tokens": 3000,
      "coverage": 0.8616666666666667,
      "happiness": 5.3410676982591445
    },
    {
      "start": 33500,
      "end": 36500,
      "tokens": 3000,
      "coverage": 0.849,
      "happiness": 5.341912053396109
    },
    {
      "start": 34000,
      "end": 37000,
      "tokens": 3000,
      "coverage": 0.846,
      "happiness": 5.321997635933771
    },
    {
      "start": 34500,
      "end": 37500,
      "tokens": 3000,
      "coverage": 0.851,
      "happiness": 5.3463454759106455
    },
    {
      "start": 35000,
      "end": 38000,
      "tokens": 3000,
      "coverage": 0.846,
      "happiness": 5.324172576832096
    },
    {
      "start": 35500,
      "end": 38500,
      "tokens": 3000,
      "coverage": 0.8423333333333334,
      "happiness": 5.310728136129748
    },
    {
      "start": 36000,
      "end": 39000,
      "tokens": 3000,
      "coverage": 0.845,
      "happiness": 5.278272189349065
    },
    {
      "start": 36500,
      "end": 39500,
      "tokens": 3000,
      "coverage": 0.8536666666666667,
      "happiness": 5.295384615384566
    },
    {
      "start": 37000,
      "end": 40000,
      "tokens": 3000,
      "coverage": 0.8626666666666667,
      "happiness": 5.32651468315297
    },
    {
      "start": 37500,
      "end": 40500,
      "tokens": 3000,
      "coverage": 0.8656666666666667,
      "happiness": 5.334682325760458
    },
    {
      "start": 38000,
      "end": 41000,
      "tokens": 3000,
      "coverage": 0.876,
      "happiness": 5.391575342465731
    },
    {
      "start": 38500,
      "end": 41500,
      "tokens": 3000,
      "coverage": 0.8773333333333333,
      "happiness": 5.436132218844956
    },
    {
      "start": 39000,
      "end": 42000,
      "tokens": 3000,
      "coverage": 0.8786666666666667,
      "happiness": 5.4757966616084675
    },
    {
      "start": 39500,
      "end": 42500,
      "tokens": 3000,
      "coverage": 0.8766666666666667,
      "happiness": 5.473357414448635
    },
    {
      "start": 40000,
      "end": 43000,
      "tokens": 3000,
      "coverage": 0.877,
      "happiness": 5.457381223869208
    },
    {
      "start": 40500,
      "end": 43500,
      "tokens": 3000,
      "coverage": 0.871,
      "happiness": 5.468090317642507
    },
    {
      "start": 41000,
      "end": 43600,
      "tokens": 2600,
      "coverage": 0.8673076923076923,
      "happiness": 5.46094013303765
    },
    {
      "start": 41500,
      "end": 43600,
      "tokens": 2100,
      "coverage": 0.8723809523809524,
      "happiness": 5.450218340611318
    },
    {
      "start": 42000,
      "end": 43600,
      "tokens": 1600,
      "coverage": 0.870625,
      "happiness": 5.433740129217502
    }
  ]
}